mlx_audio/__init__.py
mlx_audio/convert.py
mlx_audio/dsp.py
mlx_audio/server.py
mlx_audio/utils.py
mlx_audio/version.py
mlx_audio/codec/__init__.py
mlx_audio/codec/models/__init__.py
mlx_audio/codec/models/bigvgan/__init__.py
mlx_audio/codec/models/bigvgan/activation.py
mlx_audio/codec/models/bigvgan/amp.py
mlx_audio/codec/models/bigvgan/bigvgan.py
mlx_audio/codec/models/bigvgan/conv.py
mlx_audio/codec/models/bigvgan/resample.py
mlx_audio/codec/models/dacvae/__init__.py
mlx_audio/codec/models/dacvae/codec.py
mlx_audio/codec/models/descript/__init__.py
mlx_audio/codec/models/descript/base.py
mlx_audio/codec/models/descript/dac.py
mlx_audio/codec/models/descript/nn/__init__.py
mlx_audio/codec/models/descript/nn/layers.py
mlx_audio/codec/models/descript/nn/quantize.py
mlx_audio/codec/models/encodec/__init__.py
mlx_audio/codec/models/encodec/encodec.py
mlx_audio/codec/models/mimi/__init__.py
mlx_audio/codec/models/mimi/mimi.py
mlx_audio/codec/models/mimi/modules/__init__.py
mlx_audio/codec/models/mimi/modules/conv.py
mlx_audio/codec/models/mimi/modules/kv_cache.py
mlx_audio/codec/models/mimi/modules/quantization.py
mlx_audio/codec/models/mimi/modules/seanet.py
mlx_audio/codec/models/mimi/modules/transformer.py
mlx_audio/codec/models/s3gen/__init__.py
mlx_audio/codec/models/s3gen/decoder.py
mlx_audio/codec/models/s3gen/f0_predictor.py
mlx_audio/codec/models/s3gen/flow.py
mlx_audio/codec/models/s3gen/flow_matching.py
mlx_audio/codec/models/s3gen/hifigan.py
mlx_audio/codec/models/s3gen/mel.py
mlx_audio/codec/models/s3gen/s3gen.py
mlx_audio/codec/models/s3gen/xvector.py
mlx_audio/codec/models/s3gen/matcha/__init__.py
mlx_audio/codec/models/s3gen/matcha/decoder.py
mlx_audio/codec/models/s3gen/matcha/flow_matching.py
mlx_audio/codec/models/s3gen/matcha/transformer.py
mlx_audio/codec/models/s3gen/transformer/__init__.py
mlx_audio/codec/models/s3gen/transformer/activation.py
mlx_audio/codec/models/s3gen/transformer/attention.py
mlx_audio_plus-0.1.8.dist-info/licenses/LICENSE
mlx_audio_plus-0.1.8.dist-info/METADATA
mlx_audio_plus-0.1.8.dist-info/WHEEL
mlx_audio_plus-0.1.8.dist-info/entry_points.txt
mlx_audio_plus-0.1.8.dist-info/top_level.txt
mlx_audio_plus-0.1.8.dist-info/RECORD
