Metadata-Version: 2.4
Name: mlx-audio-plus
Version: 0.1.8
Summary: Python tools for text to speech (TTS), speech to text (STT), and speech to speech (STS) powered by MLX
Author-email: Anthony DePasquale <anthony@depasquale.org>, Prince Canuma <prince.gdt@gmail.com>
License: MIT
Project-URL: Homepage, https://github.com/DePasqualeOrg/mlx-audio-plus
Project-URL: Repository, https://github.com/DePasqualeOrg/mlx-audio-plus
Classifier: Programming Language :: Python :: 3
Classifier: License :: OSI Approved :: MIT License
Classifier: Operating System :: OS Independent
Requires-Python: >=3.10
License-File: LICENSE
Requires-Dist: mlx>=0.25.2
Requires-Dist: numpy>=1.26.4
Requires-Dist: huggingface_hub>=0.27.0
Requires-Dist: transformers<5.0.0,>=4.49.0
Requires-Dist: hf_transfer
Requires-Dist: mlx-lm<0.30.0,>=0.18.0
Requires-Dist: tqdm>=4.67.1
Requires-Dist: sounddevice>=0.5.1
Requires-Dist: soundfile>=0.13.1
Requires-Dist: pyloudnorm>=0.1.1
Requires-Dist: librosa==0.11.0
Requires-Dist: mlx-audio[all]
Provides-Extra: stt
Requires-Dist: tiktoken>=0.9.0; extra == "stt"
Requires-Dist: mistral-common[audio]; extra == "stt"
Provides-Extra: tts
Requires-Dist: misaki[en]>=0.8.2; extra == "tts"
Requires-Dist: loguru>=0.7.3; extra == "tts"
Requires-Dist: num2words>=0.5.14; extra == "tts"
Requires-Dist: spacy>=3.8.4; extra == "tts"
Requires-Dist: phonemizer-fork>=3.3.2; extra == "tts"
Requires-Dist: espeakng-loader>=0.2.4; extra == "tts"
Requires-Dist: sentencepiece>=0.2.0; extra == "tts"
Requires-Dist: einops>=0.8.1; extra == "tts"
Requires-Dist: omegaconf==2.3.0; extra == "tts"
Requires-Dist: einx==0.3.0; extra == "tts"
Requires-Dist: dacite>=1.9.2; extra == "tts"
Provides-Extra: server
Requires-Dist: fastapi>=0.95.0; extra == "server"
Requires-Dist: uvicorn>=0.22.0; extra == "server"
Provides-Extra: sts
Requires-Dist: mlx-audio-plus[stt,tts]; extra == "sts"
Requires-Dist: mlx-vlm>=0.1.27; extra == "sts"
Requires-Dist: fastrtc[stt,vad]==0.0.34; extra == "sts"
Requires-Dist: webrtcvad>=2.0.10; extra == "sts"
Provides-Extra: all
Requires-Dist: mlx-audio-plus[server,sts,stt,tts]; extra == "all"
Provides-Extra: dev
Requires-Dist: pytest>=7.0.0; extra == "dev"
Requires-Dist: pytest-asyncio>=1.0.0; extra == "dev"
Dynamic: license-file
